{
  "date": "2026-03-03",
  "price": 4.43,
  "change_pct": 0.0,
  "market_cap": "$444.92M",
  "beta": 1.35,
  "range_52w": "2.13 - 4.48",
  "w52_low": 2.13,
  "w52_high": 4.48,
  "w52_pos": 97.9,
  "sector": "Communication Services",
  "industry": "Internet Content & Information",
  "rev_growth": -7.8,
  "profit_margin": -3.6,
  "pe": null,
  "fwd_pe": -126.57,
  "ema_stack": "TANGLED",
  "ema_8": 4.42,
  "ema_21": 4.42,
  "ema_34": 4.38,
  "sma_20": 4.41,
  "sma_50": 4.43,
  "sma_100": 3.68,
  "sma_200": null,
  "trend": "Bullish",
  "crossover": "Golden Cross",
  "trend_short": "\u2193 Bearish",
  "trend_med": "\u2193 Bearish",
  "trend_long": "N/A",
  "rsi": 66.67,
  "adx": 44.89,
  "stoch_k": 60.0,
  "stoch_d": 67.22,
  "macd": 0.01,
  "macd_signal": 0.02,
  "macd_hist": -0.0,
  "pivot": 4.43,
  "r1": 4.44,
  "r2": 4.45,
  "s1": 4.42,
  "s2": 4.41,
  "atr": 0.02,
  "rel_vol": 1.03,
  "iv": 57.03,
  "hv": 4.0,
  "iv_rank": null,
  "iv_percentile": null,
  "fib_236": 3.93,
  "fib_382": 3.58,
  "fib_500": 3.31,
  "fib_618": 3.03,
  "kelt_upper": 4.45,
  "kelt_mid": 4.41,
  "kelt_lower": 4.37,
  "analyst_target": 3.0,
  "tv_rec": "N/A",
  "val_status": "OVERVALUED",
  "val_gap": -32.3,
  "val_target": 3.0,
  "vopr": {}
}