{
  "ticker": "TSLA",
  "companyName": "Tesla, Inc.",
  "sector": "Consumer Cyclical",
  "industry": "Auto Manufacturers",
  "currentPrice": 398.68,
  "priceChange": 1.95,
  "priceChangePct": 0.49,
  "timestamp": "2026-03-10 06:28 AM CST",
  "logo_url": "https://logo.clearbit.com/www.tesla.com",
  "generated_at": "2026-03-10 06:28 AM CST",
  "impliedVolatility": 2.1,
  "historicVolatility": 33.57,
  "ivRank": 0,
  "ivPercentile": 0,
  "trendOverall": "Bullish",
  "trendShort": "Weak",
  "trendMed": "Soft",
  "trendLong": "Strong",
  "expectedMoves": [
    {
      "expiration": "2026-03-11",
      "expectedMove": 0.79,
      "expectedRange": "397.89 - 399.47",
      "iv": 3.8,
      "dte": 1
    },
    {
      "expiration": "2026-03-13",
      "expectedMove": 0.82,
      "expectedRange": "397.86 - 399.5",
      "iv": 2.8,
      "dte": 2
    },
    {
      "expiration": "2026-03-16",
      "expectedMove": 0.98,
      "expectedRange": "397.7 - 399.66",
      "iv": 2.1,
      "dte": 5
    },
    {
      "expiration": "2026-03-18",
      "expectedMove": 1.05,
      "expectedRange": "397.63 - 399.73",
      "iv": 1.9,
      "dte": 7
    }
  ],
  "volumeStats": {
    "callVolume": 671356,
    "putVolume": 423605,
    "totalVolume": 1094961,
    "pcRatioVol": 0.63,
    "callOpenInt": 162502,
    "putOpenInt": 87881,
    "totalOpenInt": 250383,
    "pcRatioOi": 0.54
  },
  "market_snapshot": {
    "price": 398.68,
    "market_cap": "$1496.02B",
    "beta": 1.93,
    "range_52w": "346.07 - 498.83",
    "analyst_target": 421.61
  },
  "technical_analysis": {
    "trend": {
      "outlook": "Bullish",
      "sma_50": 426.27,
      "sma_200": 392.37,
      "crossover": "Golden Cross"
    },
    "ema": {
      "8": 402.19,
      "21": 409.11,
      "34": 415.25,
      "55": 420.81,
      "89": 419.93
    },
    "ema_stack": "PARTIAL BEARISH",
    "volume": {
      "current": "66,821,300",
      "avg_20d": "58,328,535",
      "rel_vol": 1.15,
      "rel_vol_pct": 57
    },
    "pivots": {
      "R2": 405.9,
      "R1": 401.32,
      "PP": 397.76,
      "S1": 393.18,
      "S2": 389.62
    },
    "fibonacci": {
      "100": 498.83,
      "61.8": 404.42,
      "50": 422.45,
      "38.2": 440.48,
      "0": 346.07
    },
    "oscillators": {
      "rsi_14": 42.71,
      "adx_14": 25.61,
      "macd_hist": -0.03,
      "stoch_k": 44.38
    }
  },
  "volatility": {
    "hv_30d": 33.57,
    "iv_current": 2.1
  },
  "valuation": {
    "status": "OVERVALUED",
    "gap_pct": -44.2,
    "target_price": 222.34,
    "method": "BLENDED (Graham+Analyst)"
  },
  "scores": {
    "technical": 75,
    "fundamental": 60,
    "grade": "B"
  },
  "tradingview": {
    "recommendation": "SELL",
    "buy": 3,
    "sell": 13,
    "neutral": 10
  },
  "insider_transactions": [
    {
      "date": "2026-02-25",
      "insider": "WILSON - THOMPSON KATHLEEN",
      "type": "",
      "value": "$10.69M"
    },
    {
      "date": "2026-02-25",
      "insider": "WILSON - THOMPSON KATHLEEN",
      "type": "",
      "value": "$599,600"
    },
    {
      "date": "2026-01-02",
      "insider": "MURDOCH JAMES RUPERT",
      "type": "",
      "value": "$26.72M"
    },
    {
      "date": "2025-12-30",
      "insider": "MUSK ELON REEVE",
      "type": "",
      "value": "$0"
    },
    {
      "date": "2025-12-09",
      "insider": "MUSK KIMBAL J",
      "type": "",
      "value": "$25.61M"
    }
  ],
  "news": [
    {
      "title": "Record Truck Profits, a $7 Billion EV Write Off, and a Market That Doesn\u2019t Care",
      "link": "https://247wallst.com/investing/2026/03/10/record-truck-profits-a-7-billion-ev-write-off-and-a-market-that-doesnt-care/?.tsrc=rss",
      "summary": "General Motors (NYSE:GM) is trading at $73.05 on Monday, down 10% year-to-date, and the number driving market mood has nothing to do with truck margin",
      "source": "Yahoo Finance"
    },
    {
      "title": "Forget YieldMax: These 4 High-Yield ETFs Are Paying Over 15% Right Now",
      "link": "https://247wallst.com/investing/2026/03/10/forget-yieldmax-these-4-high-yield-etfs-are-paying-over-15-right-now/?.tsrc=rss",
      "summary": "YieldMax gets most of the attention when income investors go hunting for double-digit yields. But the options-premium income space is wider than one f",
      "source": "Yahoo Finance"
    },
    {
      "title": "Exxon Eyes Texas for Legal Home After 144 Years in New Jersey",
      "link": "https://finance.yahoo.com/news/exxon-eyes-texas-legal-home-101000725.html?.tsrc=rss",
      "summary": "In a proxy filing on Tuesday, the oil company said moving would mean operating in a more favorable business environment where officials are more famil",
      "source": "Yahoo Finance"
    }
  ],
  "tickertrace": {
    "detail": {
      "ticker": "TSLA",
      "name": "Tesla Inc",
      "sector": "",
      "fundCount": 8,
      "holdings": [
        {
          "fund": "TSLW",
          "provider": "Roundhill",
          "weight": 11.27,
          "shares": 30737.0,
          "isOption": false
        },
        {
          "fund": "ARKK",
          "provider": "ARK Invest",
          "weight": 10.27,
          "shares": 1712422.0,
          "isOption": false
        },
        {
          "fund": "ARKQ",
          "provider": "ARK Invest",
          "weight": 10.08,
          "shares": 499549.0,
          "isOption": false
        },
        {
          "fund": "ARKW",
          "provider": "ARK Invest",
          "weight": 9.7,
          "shares": 397936.0,
          "isOption": false
        },
        {
          "fund": "EGGY",
          "provider": "Tidal / NestYield",
          "weight": 4.37,
          "shares": 8726.0,
          "isOption": false
        },
        {
          "fund": "EGGQ",
          "provider": "Tidal / NestYield",
          "weight": 4.32,
          "shares": 6283.0,
          "isOption": false
        },
        {
          "fund": "KQQQ",
          "provider": "Kurv",
          "weight": 3.47,
          "shares": 8177.0,
          "isOption": false
        },
        {
          "fund": "SLTY",
          "provider": "YieldMax",
          "weight": -3.45,
          "shares": -1400.0,
          "isOption": false
        }
      ]
    },
    "signal": {
      "direction": "buying",
      "ticker": "TSLA",
      "name": "Tesla Inc",
      "sector": "",
      "weightDelta": 11.45,
      "funds": [
        "TSLW",
        "EGGY",
        "EGGQ",
        "KQQQ",
        "SLTY"
      ],
      "providers": [
        "YieldMax",
        "Tidal / NestYield",
        "Roundhill",
        "Kurv"
      ],
      "conviction": 4.122
    }
  },
  "sec_insights": {
    "operations": "Tesla, Inc. // Consumer Cyclical [Auto Manufacturers]. Mkt Cap: $1496.02B. Rev Growth: -3.1%. PM: 4.0%.",
    "forward_looking": "Beta: 1.93. Range(52W): 346.07 - 498.83. Analyst Tgt: 421.61."
  },
  "ai_analysis": "<span class='text-neon-blue font-bold'>AI.SYNTHESIS // </span><br>Asset demonstrates a <span class=\"text-neon-green\">STRONG</span> technical posture (Score: 75/100) within a wider Bullish trend. Asset appears overvalued \u2014 exercise caution. <br><br><span class='text-gray-400 font-bold'>RISK.PROFILE // </span>Volatility within normal range. <br><br><span class='text-neon-amber font-bold'>VERDICT // </span>WAIT for validation"
}