{
  "date": "2026-03-03",
  "price": 74.7,
  "change_pct": -8.42,
  "market_cap": "$25.51B",
  "beta": null,
  "range_52w": "36.63 - 109.83",
  "w52_low": 36.63,
  "w52_high": 109.83,
  "w52_pos": 52.0,
  "sector": "N/A",
  "industry": "N/A",
  "rev_growth": 0,
  "profit_margin": 0,
  "pe": null,
  "fwd_pe": null,
  "ema_stack": "FULL BULLISH",
  "ema_8": 78.5,
  "ema_21": 77.55,
  "ema_34": 76.31,
  "sma_20": 75.1,
  "sma_50": 76.4,
  "sma_100": 62.24,
  "sma_200": null,
  "trend": "Bullish",
  "crossover": "Golden Cross",
  "trend_short": "\u2191 Bullish",
  "trend_med": "\u2191 Bullish",
  "trend_long": "N/A",
  "rsi": 51.31,
  "adx": 16.97,
  "stoch_k": 47.49,
  "stoch_d": 75.91,
  "macd": 0.77,
  "macd_signal": 0.34,
  "macd_hist": 0.43,
  "pivot": 80.76,
  "r1": 83.18,
  "r2": 84.79,
  "s1": 79.15,
  "s2": 76.73,
  "atr": 5.2,
  "rel_vol": 0.99,
  "iv": 78.52,
  "hv": 137.43,
  "iv_rank": 22.4,
  "iv_percentile": 7.3,
  "fib_236": 92.55,
  "fib_382": 81.87,
  "fib_500": 73.23,
  "fib_618": 64.59,
  "kelt_upper": 86.64,
  "kelt_mid": 75.1,
  "kelt_lower": 63.56,
  "analyst_target": null,
  "tv_rec": "N/A",
  "val_status": "UNKNOWN",
  "val_gap": 0,
  "val_target": 0,
  "vopr": {}
}