{
  "scan_date": "2026-03-11T11:27:58.879631",
  "funnel_stats": {
    "total": 696,
    "survivors": 20,
    "deep_scanned": 20,
    "elapsed_sec": 2.0,
    "mode": "market"
  },
  "a_plus_count": 4,
  "a_plus_setups": [
    {
      "ticker": "CNX",
      "name": "CNX Resources Corporation",
      "daily_grade": "A+",
      "daily_score": 5.5,
      "weekly_grade": "A",
      "weekly_score": 4.5,
      "combined_score": 10.0,
      "price": 39.84,
      "regime": "CHOP",
      "cmf": 0.123,
      "sqz_ratio": 1.22,
      "rvol": 1.51,
      "trend_phase": "MATURE"
    },
    {
      "ticker": "CTRA",
      "name": "Coterra Energy Inc.",
      "daily_grade": "B",
      "daily_score": 4.0,
      "weekly_grade": "A",
      "weekly_score": 4.8,
      "combined_score": 8.8,
      "price": 30.41,
      "regime": "CHOP",
      "cmf": -0.156,
      "sqz_ratio": 1.18,
      "rvol": 1.83,
      "trend_phase": "MATURE"
    },
    {
      "ticker": "EGY",
      "name": "VAALCO Energy, Inc.",
      "daily_grade": "B",
      "daily_score": 4.0,
      "weekly_grade": "B",
      "weekly_score": 4.2,
      "combined_score": 8.2,
      "price": 5.35,
      "regime": "CHOP",
      "cmf": 0.081,
      "sqz_ratio": 1.19,
      "rvol": 1.41,
      "trend_phase": "MATURE"
    },
    {
      "ticker": "DAR",
      "name": "Darling Ingredients Inc.",
      "daily_grade": "B",
      "daily_score": 4.0,
      "weekly_grade": "B",
      "weekly_score": 4.0,
      "combined_score": 8.0,
      "price": 52.6,
      "regime": "MODERATE",
      "cmf": 0.294,
      "sqz_ratio": 1.02,
      "rvol": 1.38,
      "trend_phase": "MATURE"
    }
  ]
}